ambient_event_bus_client/__init__.py
ambient_event_bus_client/client.py
ambient_event_bus_client/models/__init__.py
ambient_event_bus_client/models/error.py
ambient_event_bus_client/models/event_api_models.py
ambient_event_bus_client/models/messages.py
ambient_event_bus_client/models/options.py
ambient_event_bus_client-2.2.0.dist-info/METADATA
ambient_event_bus_client-2.2.0.dist-info/WHEEL
ambient_event_bus_client-2.2.0.dist-info/top_level.txt
ambient_event_bus_client-2.2.0.dist-info/RECORD
