Metadata-Version: 2.1
Name: ambient-event-bus-client
Version: 2.2.0
Summary: A library to interact with the Ambient Labs Event Bus.
Home-page: https://github.com/ambientlabscomputing/ambient-event-bus-client
Author: Jose Catarino
Author-email: jose@ambientlabscomputing.com
License: UNKNOWN
Platform: UNKNOWN
Classifier: Programming Language :: Python :: 3
Classifier: License :: OSI Approved :: MIT License
Classifier: Operating System :: OS Independent
Requires-Python: >=3.9
Requires-Dist: aiohttp==3.9.5
Requires-Dist: websockets==12.0
Requires-Dist: pydantic==2.7.4
Requires-Dist: result==0.17.0
